smpl2/__init__.py
smpl2/debug/__init__.py
smpl2/debug/debug.py
smpl2/doc/__init__.py
smpl2/doc/doc.py
smpl2/fit/__init__.py
smpl2/fit/fit.py
smpl2/functions/__init__.py
smpl2/functions/functions.py
smpl2/io/__init__.py
smpl2/io/io.py
smpl2/latex/__init__.py
smpl2/latex/latex.py
smpl2/parallel/__init__.py
smpl2/parallel/parallel.py
smpl2/plot/__init__.py
smpl2/plot/plot.py
smpl2/stat/__init__.py
smpl2/stat/stat.py
smpl2/units/__init__.py
smpl2/units/units.py
smpl2/util/__init__.py
smpl2/util/util.py
smpl2/wrap/__init__.py
smpl2/wrap/wrap.py
smpl2-0.1.0.dist-info/LICENSE
smpl2-0.1.0.dist-info/METADATA
smpl2-0.1.0.dist-info/WHEEL
smpl2-0.1.0.dist-info/top_level.txt
smpl2-0.1.0.dist-info/RECORD
