Metadata-Version: 2.1
Name: smpl2
Version: 0.1.0
Summary: simple plotting and fitting and simulation
Home-page: https://github.com/dfb159/smpl2
Author: dfb159
Author-email: jSigrist@web.de
License: UNKNOWN
Platform: UNKNOWN
Classifier: Programming Language :: Python :: 3
Classifier: License :: OSI Approved :: GNU General Public License v3 (GPLv3)
Classifier: Operating System :: OS Independent
Requires-Python: >=3.6
License-File: LICENSE
Requires-Dist: uncertainties
Requires-Dist: numpy
Requires-Dist: matplotlib
Requires-Dist: scipy
Requires-Dist: sympy
